Metadata-Version: 2.1
Name: obswx
Version: 0.0.1
Summary: A Python package for accessing observational meteorological data
Home-page: https://github.com/envdes/obswx
Author: Junjie Yu
Author-email: yjj1997@live.cn
License: MIT
Platform: UNKNOWN
Classifier: Development Status :: 2 - Pre-Alpha
Classifier: Intended Audience :: Science/Research
Classifier: License :: OSI Approved :: MIT License
Classifier: Natural Language :: English
Classifier: Operating System :: OS Independent
Classifier: Programming Language :: Python :: 3
Classifier: Topic :: Scientific/Engineering :: Atmospheric Science
License-File: LICENSE
